mcp_server/__init__.py
mcp_server/server.py
mseep_devbrain-1.1.11.dist-info/licenses/LICENSE
mseep_devbrain-1.1.11.dist-info/METADATA
mseep_devbrain-1.1.11.dist-info/WHEEL
mseep_devbrain-1.1.11.dist-info/entry_points.txt
mseep_devbrain-1.1.11.dist-info/top_level.txt
mseep_devbrain-1.1.11.dist-info/RECORD
